auth_plugin/__init__.py
auth_plugin/base_auth.py
auth_plugin/config.py
auth_plugin/db_manager.py
auth_plugin/jwt_auth.py
auth_plugin/oauth2_auth.py
auth_plugin/utils.py
tests/__init__.py
tests/test_db_manager.py
tests/test_jwt_auth.py
tests/test_oauth2_auth.py
tests/test_utils.py
auth_plugin-0.3.1.dist-info/LICENSE
auth_plugin-0.3.1.dist-info/METADATA
auth_plugin-0.3.1.dist-info/WHEEL
auth_plugin-0.3.1.dist-info/top_level.txt
auth_plugin-0.3.1.dist-info/RECORD
