Metadata-Version: 2.1
Name: auth-plugin
Version: 0.3.1
Summary: A robust Python library for JWT, OAuth2, and database authentication.
Home-page: https://github.com/viseshagarwal/auth-plugin
Author: Visesh Agarwal
Classifier: Programming Language :: Python :: 3
Classifier: License :: OSI Approved :: MIT License
Classifier: Operating System :: OS Independent
Requires-Python: >=3.6
License-File: LICENSE
Requires-Dist: PyJWT
Requires-Dist: pymongo
Requires-Dist: SQLAlchemy
Requires-Dist: mysql-connector-python
Requires-Dist: requests
Requires-Dist: psycopg2
Requires-Dist: cryptography
Requires-Dist: certifi
Requires-Dist: cffi
